<?xml version="1.0" encoding="UTF-8"?>
<alquileres>
    <alquiler>
        <socio>1001</socio>
        <copia_pelicula>101</copia_pelicula>
        <fecha_alquiler>2017-11-28</fecha_alquiler>
        <fecha_devolucion>2017-11-29</fecha_devolucion>
    </alquiler>
    <alquiler>
        <socio>1001</socio>
        <copia_pelicula>108</copia_pelicula>
        <fecha_alquiler>2017-12-01</fecha_alquiler>
        <fecha_devolucion>2017-12-03</fecha_devolucion>
    </alquiler>
    <alquiler>
        <socio>1001</socio>
        <copia_pelicula>112</copia_pelicula>
        <fecha_alquiler>2017-11-29</fecha_alquiler>
        <fecha_devolucion>2017-11-30</fecha_devolucion>
    </alquiler>
    <alquiler>
        <socio>1001</socio>
        <copia_pelicula>113</copia_pelicula>
        <fecha_alquiler>2017-10-09</fecha_alquiler>
        <fecha_devolucion>2017-10-10</fecha_devolucion>
    </alquiler>
    <alquiler>
        <socio>1002</socio>
        <copia_pelicula>103</copia_pelicula>
        <fecha_alquiler>2017-11-29</fecha_alquiler>
        <fecha_devolucion>2017-11-30</fecha_devolucion>
    </alquiler>
    <alquiler>
        <socio>1002</socio>
        <copia_pelicula>106</copia_pelicula>
        <fecha_alquiler>2017-12-07</fecha_alquiler>
        <fecha_devolucion>2017-12-10</fecha_devolucion>
    </alquiler>
    <alquiler>
        <socio>1003</socio>
        <copia_pelicula>107</copia_pelicula>
        <fecha_alquiler>2017-11-28</fecha_alquiler>
        <fecha_devolucion>2017-11-29</fecha_devolucion>
    </alquiler>
    <alquiler>
        <socio>1003</socio>
        <copia_pelicula>109</copia_pelicula>
        <fecha_alquiler>2017-11-15</fecha_alquiler>
        <fecha_devolucion>2017-11-16</fecha_devolucion>
    </alquiler>
    <alquiler>
        <socio>1004</socio>
        <copia_pelicula>104</copia_pelicula>
        <fecha_alquiler>2017-11-29</fecha_alquiler>
        <fecha_devolucion>2017-11-30</fecha_devolucion>
    </alquiler>
    <alquiler>
        <socio>1004</socio>
        <copia_pelicula>109</copia_pelicula>
        <fecha_alquiler>2017-12-28</fecha_alquiler>
        <fecha_devolucion>2017-12-29</fecha_devolucion>
    </alquiler>
    <alquiler>
        <socio>1005</socio>
        <copia_pelicula>102</copia_pelicula>
        <fecha_alquiler>2017-11-24</fecha_alquiler>
        <fecha_devolucion>2017-11-25</fecha_devolucion>
    </alquiler>
    <alquiler>
        <socio>1005</socio>
        <copia_pelicula>104</copia_pelicula>
        <fecha_alquiler>2017-12-01</fecha_alquiler>
        <fecha_devolucion>2017-12-02</fecha_devolucion>
    </alquiler>
    <alquiler>
        <socio>1005</socio>
        <copia_pelicula>107</copia_pelicula>
        <fecha_alquiler>2017-11-28</fecha_alquiler>
        <fecha_devolucion>2017-11-29</fecha_devolucion>
    </alquiler>
    <alquiler>
        <socio>1005</socio>
        <copia_pelicula>107</copia_pelicula>
        <fecha_alquiler>2017-12-05</fecha_alquiler>
        <fecha_devolucion>2017-12-06</fecha_devolucion>
    </alquiler>
    <alquiler>
        <socio>1005</socio>
        <copia_pelicula>111</copia_pelicula>
        <fecha_alquiler>2017-11-13</fecha_alquiler>
        <fecha_devolucion>2017-11-14</fecha_devolucion>
    </alquiler>
    <alquiler>
        <socio>1006</socio>
        <copia_pelicula>110</copia_pelicula>
        <fecha_alquiler>2017-10-01</fecha_alquiler>
        <fecha_devolucion>2017-10-04</fecha_devolucion>
    </alquiler>
    <alquiler>
        <socio>1006</socio>
        <copia_pelicula>112</copia_pelicula>
        <fecha_alquiler>2017-10-01</fecha_alquiler>
        <fecha_devolucion>2017-10-04</fecha_devolucion>
    </alquiler>
</alquileres>
